cribl_mgmt_plane/__init__.py
cribl_mgmt_plane/_hooks/__init__.py
cribl_mgmt_plane/_hooks/clientcredentials.py
cribl_mgmt_plane/_hooks/registration.py
cribl_mgmt_plane/_hooks/sdkhooks.py
cribl_mgmt_plane/_hooks/types.py
cribl_mgmt_plane/_version.py
cribl_mgmt_plane/basesdk.py
cribl_mgmt_plane/errors/__init__.py
cribl_mgmt_plane/errors/apierror.py
cribl_mgmt_plane/errors/criblmgmtplaneerror.py
cribl_mgmt_plane/errors/no_response_error.py
cribl_mgmt_plane/errors/responsevalidationerror.py
cribl_mgmt_plane/health.py
cribl_mgmt_plane/httpclient.py
cribl_mgmt_plane/models/__init__.py
cribl_mgmt_plane/models/defaulterrordto.py
cribl_mgmt_plane/models/gethealthstatusop.py
cribl_mgmt_plane/models/schemeclientoauth.py
cribl_mgmt_plane/models/security.py
cribl_mgmt_plane/models/v1_workspaces_createworkspaceop.py
cribl_mgmt_plane/models/v1_workspaces_deleteworkspaceop.py
cribl_mgmt_plane/models/v1_workspaces_getworkspaceop.py
cribl_mgmt_plane/models/v1_workspaces_listworkspacesop.py
cribl_mgmt_plane/models/v1_workspaces_updateworkspaceop.py
cribl_mgmt_plane/models/workspacecreaterequestdto.py
cribl_mgmt_plane/models/workspacepatchrequestdto.py
cribl_mgmt_plane/models/workspaceschema.py
cribl_mgmt_plane/models/workspaceslistresponsedto.py
cribl_mgmt_plane/py.typed
cribl_mgmt_plane/sdk.py
cribl_mgmt_plane/sdkconfiguration.py
cribl_mgmt_plane/types/__init__.py
cribl_mgmt_plane/types/basemodel.py
cribl_mgmt_plane/utils/__init__.py
cribl_mgmt_plane/utils/annotations.py
cribl_mgmt_plane/utils/datetimes.py
cribl_mgmt_plane/utils/enums.py
cribl_mgmt_plane/utils/eventstreaming.py
cribl_mgmt_plane/utils/forms.py
cribl_mgmt_plane/utils/headers.py
cribl_mgmt_plane/utils/logger.py
cribl_mgmt_plane/utils/metadata.py
cribl_mgmt_plane/utils/queryparams.py
cribl_mgmt_plane/utils/requestbodies.py
cribl_mgmt_plane/utils/retries.py
cribl_mgmt_plane/utils/security.py
cribl_mgmt_plane/utils/serializers.py
cribl_mgmt_plane/utils/unmarshal_json_response.py
cribl_mgmt_plane/utils/url.py
cribl_mgmt_plane-0.2.0.dist-info/METADATA
cribl_mgmt_plane-0.2.0.dist-info/WHEEL
cribl_mgmt_plane-0.2.0.dist-info/RECORD
